wkls/__init__.py
wkls/core.py
wkls/data/__init__.py
wkls/data/overture_land.zstd.parquet
wkls-0.4.5.dist-info/licenses/LICENCE
wkls-0.4.5.dist-info/METADATA
wkls-0.4.5.dist-info/WHEEL
wkls-0.4.5.dist-info/top_level.txt
wkls-0.4.5.dist-info/RECORD
