Metadata-Version: 2.4
Name: wkls
Version: 0.4.5
Summary: Easy access to global administrative boundaries and geometries via Overture Maps data
Author-email: Pranav Toggi <pranav@wherobots.com>, Maxime Petazzoni <max@wherobots.com>, Matthew Powers <mpowers@wherobots.com>
License-Expression: Apache-2.0
Project-URL: Homepage, https://github.com/wherobots/wkls
Project-URL: Repository, https://github.com/wherobots/wkls.git
Project-URL: Issues, https://github.com/wherobots/wkls/issues
Project-URL: Documentation, https://github.com/wherobots/wkls#readme
Project-URL: Changelog, https://github.com/wherobots/wkls/releases
Keywords: gis,geography,boundaries,geospatial,overture-maps,wkt,geometry,admin boundaries,geojson,spatial
Classifier: Development Status :: 4 - Beta
Classifier: Intended Audience :: Developers
Classifier: Intended Audience :: Science/Research
Classifier: Operating System :: OS Independent
Classifier: Programming Language :: Python :: 3
Classifier: Programming Language :: Python :: 3.9
Classifier: Programming Language :: Python :: 3.10
Classifier: Programming Language :: Python :: 3.11
Classifier: Programming Language :: Python :: 3.12
Classifier: Programming Language :: Python :: 3.13
Classifier: Topic :: Scientific/Engineering :: GIS
Classifier: Topic :: Software Development :: Libraries :: Python Modules
Requires-Python: >=3.9
License-File: LICENCE
Requires-Dist: duckdb>=1.3.0
Requires-Dist: pandas>=1.5.0
Dynamic: license-file
